imWeightedThresholdedheq.py
imWeightedThresholdedheq-1.0.2.data/scripts/imWeightedThresholdedheq
imWeightedThresholdedheq-1.0.2.data/scripts/vidWeightedThresholdedheq
imWeightedThresholdedheq-1.0.2.dist-info/LICENSE
imWeightedThresholdedheq-1.0.2.dist-info/METADATA
imWeightedThresholdedheq-1.0.2.dist-info/WHEEL
imWeightedThresholdedheq-1.0.2.dist-info/top_level.txt
imWeightedThresholdedheq-1.0.2.dist-info/RECORD
