Metadata-Version: 2.1
Name: imWeightedThresholdedheq
Version: 1.0.2
Summary: This module attempts to enhance contrast of a given image by employing a method called weighted thresholded histogram equalization (WTHE).
Home-page: https://github.com/Mamdasn/imWeightedThresholdedheq
Author: mamdasn s
Author-email: <mamdassn@gmail.com>
Keywords: python,histogram,HE,hist equalization,histogram based equalization,weighted thresholded histogram equalization,contrast enhancement
Classifier: Development Status :: 3 - Alpha
Classifier: Intended Audience :: Science/Research
Classifier: License :: OSI Approved :: GNU General Public License v3 (GPLv3)
Classifier: Programming Language :: Python :: 3.8
Classifier: Operating System :: OS Independent
License-File: LICENSE
Requires-Dist: numpy
Requires-Dist: numba
Requires-Dist: opencv-python
Requires-Dist: tqdm
